dwarfgirrafe/__init__.py
dwarfgirrafe/module.py
dwarfgirrafe-1.0.3.dist-info/METADATA
dwarfgirrafe-1.0.3.dist-info/WHEEL
dwarfgirrafe-1.0.3.dist-info/top_level.txt
dwarfgirrafe-1.0.3.dist-info/RECORD
