Metadata-Version: 2.4
Name: dwarfgirrafe
Version: 1.0.3
Summary: with great power comes great responsibilities
Author: Bhavesh Patil
Author-email: bhaveshpatil7504@gmail.com
Classifier: Programming Language :: Python :: 3
Classifier: License :: OSI Approved :: MIT License
Classifier: Operating System :: OS Independent
Requires-Python: >=3.0
Dynamic: author
Dynamic: author-email
Dynamic: classifier
Dynamic: requires-python
Dynamic: summary
